demo/__init__.py
demo/forms.py
demo/views.py
great_components/__init__.py
great_components/constants.py
great_components/context_processors.py
great_components/decorators.py
great_components/helpers.py
great_components/middleware.py
great_components/mixins.py
great_components/views.py
great_components/forms/__init__.py
great_components/forms/fields.py
great_components/forms/forms.py
great_components/forms/widgets.py
great_components/janitor/__init__.py
great_components/janitor/management/__init__.py
great_components/janitor/management/commands/__init__.py
great_components/janitor/management/commands/environment_diff.py
great_components/janitor/management/commands/helpers.py
great_components/janitor/management/commands/settings_shake.py
great_components/janitor/management/commands/vault_diff.py
great_components/janitor/management/commands/vault_update.py
great_components/locale/de/LC_MESSAGES/django.mo
great_components/locale/de/LC_MESSAGES/django.po
great_components/locale/es/LC_MESSAGES/django.mo
great_components/locale/es/LC_MESSAGES/django.po
great_components/locale/fr/LC_MESSAGES/django.mo
great_components/locale/fr/LC_MESSAGES/django.po
great_components/locale/ja/LC_MESSAGES/django.mo
great_components/locale/ja/LC_MESSAGES/django.po
great_components/locale/pt/LC_MESSAGES/django.mo
great_components/locale/pt/LC_MESSAGES/django.po
great_components/locale/zh_Hans/LC_MESSAGES/django.mo
great_components/locale/zh_Hans/LC_MESSAGES/django.po
great_components/static/great_components/icons/email.svg
great_components/static/great_components/icons/facebook.svg
great_components/static/great_components/icons/linkedin.svg
great_components/static/great_components/icons/twitter.svg
great_components/static/great_components/images/dfit-logo-white.png
great_components/static/great_components/images/dit-logo.svg
great_components/static/great_components/images/eig-logo-stacked.svg
great_components/static/great_components/images/favicon-192x192.png
great_components-2.9.1.dist-info/licenses/LICENSE
great_components-2.9.1.dist-info/METADATA
great_components-2.9.1.dist-info/WHEEL
great_components-2.9.1.dist-info/top_level.txt
great_components-2.9.1.dist-info/RECORD
