Metadata-Version: 2.4
Name: great_components
Version: 2.9.1
Summary: Shared components library for Great services.
Home-page: https://github.com/uktrade/great-components
Author: DIT
License: MIT
Classifier: Development Status :: 5 - Production/Stable
Classifier: Environment :: Web Environment
Classifier: Framework :: Django
Classifier: Framework :: Django :: 1.11
Classifier: Framework :: Django :: 2.0
Classifier: Framework :: Django :: 2.1
Classifier: Framework :: Django :: 2.2
Classifier: Framework :: Django :: 3.2
Classifier: Framework :: Django :: 4.2
Classifier: Intended Audience :: Developers
Classifier: License :: OSI Approved :: MIT License
Classifier: Natural Language :: English
Classifier: Operating System :: OS Independent
Classifier: Programming Language :: Python :: 3.6
Classifier: Programming Language :: Python :: 3.9
Classifier: Programming Language :: Python :: 3.13
Classifier: Topic :: Software Development :: Libraries :: Python Modules
License-File: LICENSE
Requires-Dist: django<5.0,>=4.2.10
Requires-Dist: beautifulsoup4<5.0.0,>=4.6.0
Requires-Dist: directory-constants<25.0,>=24.1.1
Requires-Dist: jsonschema<4.0.0,>=3.0.1
Provides-Extra: test
Requires-Dist: lorem==0.1.1; extra == "test"
Requires-Dist: ansicolors==1.1.8; extra == "test"
Requires-Dist: gitdb==4.0.10; extra == "test"
Requires-Dist: gitpython==3.1.31; extra == "test"
Requires-Dist: GitPython; extra == "test"
Requires-Dist: flake8==3.7.8; extra == "test"
Requires-Dist: smmap==5.0.0; extra == "test"
Requires-Dist: toml==0.10.2; extra == "test"
Requires-Dist: requests-toolbelt; extra == "test"
Requires-Dist: twine; extra == "test"
Requires-Dist: wheel<1.0.0,>=0.31.0; extra == "test"
Requires-Dist: setuptools; extra == "test"
Requires-Dist: vulture<2.0.0,>=1.0.0; extra == "test"
Requires-Dist: hvac<1.0.0,>=0.9.5; extra == "test"
Requires-Dist: attrs==23.1.0; extra == "test"
Requires-Dist: certifi==2022.12.7; extra == "test"
Requires-Dist: charset-normalizer==3.1.0; extra == "test"
Requires-Dist: coverage[toml]==7.2.5; extra == "test"
Requires-Dist: execnet==1.9.0; extra == "test"
Requires-Dist: idna==3.4; extra == "test"
Requires-Dist: iniconfig==2.0.0; extra == "test"
Requires-Dist: packaging==23.1; extra == "test"
Requires-Dist: pluggy==0.13.1; extra == "test"
Requires-Dist: py==1.11.0; extra == "test"
Requires-Dist: pytest; extra == "test"
Requires-Dist: pytest-codecov==0.5.1; extra == "test"
Requires-Dist: pytest-cov==4.0.0; extra == "test"
Requires-Dist: pytest-django==3.10.0; extra == "test"
Requires-Dist: pytest-sugar==0.9.7; extra == "test"
Requires-Dist: pytest-xdist==3.2.1; extra == "test"
Requires-Dist: requests; extra == "test"
Requires-Dist: termcolor==2.3.0; extra == "test"
Requires-Dist: toml==0.10.2; extra == "test"
Requires-Dist: tomli==2.0.1; extra == "test"
Requires-Dist: urllib3==2.5.0; extra == "test"
Requires-Dist: codecov; extra == "test"
Provides-Extra: demo
Requires-Dist: lorem==0.1.1; extra == "demo"
Requires-Dist: django-environ==0.4.5; extra == "demo"
Requires-Dist: gunicorn==19.5.0; extra == "demo"
Requires-Dist: whitenoise==6.4.0; extra == "demo"
Requires-Dist: django-pygments==0.3.0; extra == "demo"
Provides-Extra: janitor
Requires-Dist: ansicolors<2.0.0,>=1.1.8; extra == "janitor"
Dynamic: author
Dynamic: classifier
Dynamic: description
Dynamic: description-content-type
Dynamic: home-page
Dynamic: license
Dynamic: license-file
Dynamic: provides-extra
Dynamic: requires-dist
Dynamic: summary
